simple_authorizer/__init__.py
simple_authorizer/authorizer.py
amazon_api_gateway_simple_authorizer-0.1.0.dist-info/LICENSE
amazon_api_gateway_simple_authorizer-0.1.0.dist-info/METADATA
amazon_api_gateway_simple_authorizer-0.1.0.dist-info/WHEEL
amazon_api_gateway_simple_authorizer-0.1.0.dist-info/top_level.txt
amazon_api_gateway_simple_authorizer-0.1.0.dist-info/RECORD
