Metadata-Version: 2.1
Name: amazon-api-gateway-simple-authorizer
Version: 0.1.0
Summary: Simple Lambda authorizer for HTTP API behind CloudFront
Home-page: https://github.com/efficient-solutions/amazon-api-gateway-simple-authorizer
Author: Efficient Solutions LLC
Author-email: contact@efficient.solutions
License: MIT
Keywords: Amazon API Gateway,Amazon CloudFront,AWS Lambda
Classifier: Intended Audience :: Developers
Classifier: Natural Language :: English
Classifier: License :: OSI Approved :: MIT License
Classifier: Programming Language :: Python
Classifier: Programming Language :: Python :: 3
Classifier: Programming Language :: Python :: 3 :: Only
Classifier: Programming Language :: Python :: 3.10
Classifier: Programming Language :: Python :: 3.11
Classifier: Programming Language :: Python :: 3.12
Requires-Python: >= 3.10
License-File: LICENSE
